MANIFEST.in
README.txt
setup.py
ISY/IsyClass.py
ISY/IsyDebug.py
ISY/IsyDiscover.py
ISY/IsyEvent.py
ISY/IsyEventData.py
ISY/IsyExceptionClass.py
ISY/IsyNodeClass.py
ISY/IsyProgramClass.py
ISY/IsyUtilClass.py
ISY/IsyVarClass.py
ISY/__init__.py
ISY/_isyclimate.py
ISY/_isynet_resources.py
ISY/_isynode.py
ISY/_isyprog.py
ISY/_isyvar.py
ISY/_isyzb.py
ISYlib.egg-info/PKG-INFO
ISYlib.egg-info/SOURCES.txt
ISYlib.egg-info/dependency_links.txt
ISYlib.egg-info/top_level.txt
bin/isy_audit_pgm_var.py
bin/isy_audit_pgm_x10.py
bin/isy_audit_x10_use.py
bin/isy_backup.py
bin/isy_find.py
bin/isy_log.py
bin/isy_manage_node.py
bin/isy_nestset.py
bin/isy_net_res.py
bin/isy_net_wol.py
bin/isy_nodes.py
bin/isy_progs.py
bin/isy_showevents.py
bin/isy_var.py
bin/isy_web.py
bin/nodes.py
bin/scapy-watch.py
docs/Using_IsyNode_Class.txt
docs/Using_IsyProg_Class
docs/Using_IsyVar_Class.txt
docs/Using_Isy_Class.txt