Metadata-Version: 1.1
Name: ISYlib
Version: 0.1.20150912c
Summary: Python API for the ISY home automation controller.
Home-page: https://github.com/evilpete/ISYlib-python
Author: Peter Shipley
Author-email: Peter.Shipley@gmail.com
License: BSD
Download-URL: https://github.com/evilpete/ISYlib-python/archive/0.1.20150912.tar.gz
Platform: UNKNOWN
